PUK/Joker.py
PUK/__init__.py
puk-0.2.dist-info/licenses/LICENSE
puk-0.2.dist-info/METADATA
puk-0.2.dist-info/WHEEL
puk-0.2.dist-info/top_level.txt
puk-0.2.dist-info/RECORD
