Metadata-Version: 2.4
Name: PUK
Version: 0.2
Summary: Simple
Author: Ibn-Suleiman
Author-email: tvvvyvv@gmail.com
Classifier: Programming Language :: Python :: 3
Classifier: License :: OSI Approved :: MIT License
Classifier: Operating System :: OS Independent
License-File: LICENSE
Dynamic: author
Dynamic: author-email
Dynamic: classifier
Dynamic: license-file
Dynamic: summary
